reshare/__init__.py
reshare/helpers.py
reshare/py.typed
reshare-0.1.3.dist-info/licenses/LICENSE
reshare-0.1.3.dist-info/METADATA
reshare-0.1.3.dist-info/WHEEL
reshare-0.1.3.dist-info/top_level.txt
reshare-0.1.3.dist-info/RECORD
