Metadata-Version: 2.4
Name: reshare
Version: 0.1.3
Summary: REshare reverse-engineering exchange format Python package
Author-email: buherator <buherator@scrapco.de>
License-Expression: MIT
Project-URL: Repository, https://github.com/v-p-b/reshare/python/
License-File: LICENSE
Dynamic: license-file
